Metadata-Version: 2.1
Name: trailer-downloader
Version: 1.0.0
Summary: Downloader of trailers for films/series
Home-page: https://github.com/Steelataure/Trailer-downloader
Author: Alexandre Buisset
Author-email: alexandre0312@orange.fr
License: MIT
Keywords: trailer,downloader
Classifier: License :: OSI Approved :: MIT License
Classifier: Programming Language :: Python :: 3
Classifier: Programming Language :: Python :: 3.6
Classifier: Programming Language :: Python :: 3.7
Classifier: Programming Language :: Python :: 3.8
Classifier: Programming Language :: Python :: 3.9
